ccl_localstoragers.py
ccl_localstoragers-1.1.1.dist-info/LICENSE
ccl_localstoragers-1.1.1.dist-info/METADATA
ccl_localstoragers-1.1.1.dist-info/WHEEL
ccl_localstoragers-1.1.1.dist-info/RECORD
