Metadata-Version: 2.1
Name: ccl_localstoragers
Version: 1.1.1
Summary: CCL ccl_localstorage Reader, extract vault data from any chrome extensions, and etc.
License: MIT
Author: Isaac Florentine
Requires-Python: >=3.7,<4.0
Classifier: License :: OSI Approved :: MIT License
Classifier: Programming Language :: Python :: 3
Classifier: Programming Language :: Python :: 3.7
Classifier: Programming Language :: Python :: 3.8
Classifier: Programming Language :: Python :: 3.9
Classifier: Programming Language :: Python :: 3.10
Classifier: Programming Language :: Python :: 3.11
Classifier: Programming Language :: Python :: 3.12
Requires-Dist: ccl_leveldbase (>=1.0,<2.0)
